whopy/__init__.py
whopy/airports.dat
whopy/countries.dat
whopy/countries3.dat
whopy/net.py
whopy/parse.py
whopy/shared.py
whopy/states_au.dat
whopy/states_ca.dat
whopy/states_us.dat
whopy/tld.json
whopy-0.1.dist-info/LICENSE
whopy-0.1.dist-info/METADATA
whopy-0.1.dist-info/WHEEL
whopy-0.1.dist-info/top_level.txt
whopy-0.1.dist-info/RECORD
