Metadata-Version: 2.1
Name: whopy
Version: 0.1
Summary: Module for retrieving and parsing the WHOIS data for a domain. Supports most domains. No dependencies.
Home-page: http://cryto.net/whopy
Author: Andrew Shamah
Author-email: amshamah@gmail.com
License: MIT
Platform: UNKNOWN
Provides: whopy
Requires-Dist: argparse
